restfy/__init__.py
restfy/application.py
restfy/cors.py
restfy/file.py
restfy/handler.py
restfy/http.py
restfy/middleware.py
restfy/request.py
restfy/response.py
restfy/router.py
restfy/server.py
restfy/testing.py
restfy/websocket.py
restfy-0.4.1.dist-info/LICENSE
restfy-0.4.1.dist-info/METADATA
restfy-0.4.1.dist-info/WHEEL
restfy-0.4.1.dist-info/RECORD
