Metadata-Version: 2.1
Name: restfy
Version: 0.4.1
Summary: A small rest framework
Home-page: https://github.com/manasseslima/restfy
License: MIT
Author: Manasses Lima
Author-email: manasseslima@gmail.com
Requires-Python: >=3.10,<4.0
Classifier: License :: OSI Approved :: MIT License
Classifier: Programming Language :: Python :: 3
Classifier: Programming Language :: Python :: 3.10
Classifier: Programming Language :: Python :: 3.11
Requires-Dist: bike (>=0.3.2,<0.4.0)
Requires-Dist: httplus (>=0.1.0,<0.2.0)
Project-URL: Repository, https://github.com/manasseslima/restfy
